MANIFEST.in
README.rst
setup.cfg
setup.py
ginsfsm/__init__.py
ginsfsm/buffers.py
ginsfsm/c_connex.py
ginsfsm/c_sock.py
ginsfsm/c_srv_sock.py
ginsfsm/c_stdin.py
ginsfsm/c_timer.py
ginsfsm/circular_fifo.py
ginsfsm/compat.py
ginsfsm/deferred.py
ginsfsm/dl_list.py
ginsfsm/escape.py
ginsfsm/gaplic.py
ginsfsm/gconfig.py
ginsfsm/globals.py
ginsfsm/gmsg.py
ginsfsm/gobj.py
ginsfsm/paster.py
ginsfsm/router.py
ginsfsm/smachine.py
ginsfsm/sphinxext.py
ginsfsm/threadlocal.py
ginsfsm/utils.py
ginsfsm.egg-info/PKG-INFO
ginsfsm.egg-info/SOURCES.txt
ginsfsm.egg-info/dependency_links.txt
ginsfsm.egg-info/entry_points.txt
ginsfsm.egg-info/not-zip-safe
ginsfsm.egg-info/requires.txt
ginsfsm.egg-info/top_level.txt
ginsfsm/examples/__init__.py
ginsfsm/examples/__init__.pyc
ginsfsm/examples/essential_gobjs/__init__.py
ginsfsm/examples/essential_gobjs/__init__.pyc
ginsfsm/examples/essential_gobjs/ongconnex.py
ginsfsm/examples/essential_gobjs/ongconnex.pyc
ginsfsm/examples/essential_gobjs/ongsock.py
ginsfsm/examples/essential_gobjs/ongsock.pyc
ginsfsm/examples/essential_gobjs/ontimer.py
ginsfsm/examples/essential_gobjs/ontimer.pyc
ginsfsm/examples/essential_gobjs/stress_client_echo.py
ginsfsm/examples/essential_gobjs/stress_client_echo.pyc
ginsfsm/examples/essential_gobjs/stress_connections.py
ginsfsm/examples/essential_gobjs/stress_connections.pyc
ginsfsm/examples/essential_gobjs/stress_server_echo.py
ginsfsm/examples/essential_gobjs/stress_server_echo.pyc
ginsfsm/examples/http/__init__.py
ginsfsm/examples/http/simple_http_server.py
ginsfsm/examples/inter_event/README.txt
ginsfsm/examples/inter_event/__init__.py
ginsfsm/examples/inter_event/__init__.pyc
ginsfsm/examples/inter_event/ap1.sh
ginsfsm/examples/inter_event/ap2.sh
ginsfsm/examples/inter_event/ap3.sh
ginsfsm/examples/inter_event/ap4.sh
ginsfsm/examples/inter_event/inter_event_schema.png
ginsfsm/examples/inter_event/schema.svg
ginsfsm/examples/inter_event/ap1_banco/CHANGES.txt
ginsfsm/examples/inter_event/ap1_banco/MANIFEST.in
ginsfsm/examples/inter_event/ap1_banco/README.rst
ginsfsm/examples/inter_event/ap1_banco/banco.ini
ginsfsm/examples/inter_event/ap1_banco/setup.cfg
ginsfsm/examples/inter_event/ap1_banco/setup.py
ginsfsm/examples/inter_event/ap1_banco/banco.egg-info/PKG-INFO
ginsfsm/examples/inter_event/ap1_banco/banco.egg-info/SOURCES.txt
ginsfsm/examples/inter_event/ap1_banco/banco.egg-info/dependency_links.txt
ginsfsm/examples/inter_event/ap1_banco/banco.egg-info/entry_points.txt
ginsfsm/examples/inter_event/ap1_banco/banco.egg-info/not-zip-safe
ginsfsm/examples/inter_event/ap1_banco/banco.egg-info/requires.txt
ginsfsm/examples/inter_event/ap1_banco/banco.egg-info/top_level.txt
ginsfsm/examples/inter_event/ap2_financiera/financiera.egg-info/PKG-INFO
ginsfsm/examples/inter_event/ap2_financiera/financiera.egg-info/SOURCES.txt
ginsfsm/examples/inter_event/ap2_financiera/financiera.egg-info/dependency_links.txt
ginsfsm/examples/inter_event/ap2_financiera/financiera.egg-info/entry_points.txt
ginsfsm/examples/inter_event/ap2_financiera/financiera.egg-info/not-zip-safe
ginsfsm/examples/inter_event/ap2_financiera/financiera.egg-info/requires.txt
ginsfsm/examples/inter_event/ap2_financiera/financiera.egg-info/top_level.txt
ginsfsm/examples/inter_event/ap3_bolsa/bolsa.egg-info/PKG-INFO
ginsfsm/examples/inter_event/ap3_bolsa/bolsa.egg-info/SOURCES.txt
ginsfsm/examples/inter_event/ap3_bolsa/bolsa.egg-info/dependency_links.txt
ginsfsm/examples/inter_event/ap3_bolsa/bolsa.egg-info/entry_points.txt
ginsfsm/examples/inter_event/ap3_bolsa/bolsa.egg-info/not-zip-safe
ginsfsm/examples/inter_event/ap3_bolsa/bolsa.egg-info/requires.txt
ginsfsm/examples/inter_event/ap3_bolsa/bolsa.egg-info/top_level.txt
ginsfsm/examples/inter_event/ap4_publicidad/publicidad.egg-info/PKG-INFO
ginsfsm/examples/inter_event/ap4_publicidad/publicidad.egg-info/SOURCES.txt
ginsfsm/examples/inter_event/ap4_publicidad/publicidad.egg-info/dependency_links.txt
ginsfsm/examples/inter_event/ap4_publicidad/publicidad.egg-info/entry_points.txt
ginsfsm/examples/inter_event/ap4_publicidad/publicidad.egg-info/not-zip-safe
ginsfsm/examples/inter_event/ap4_publicidad/publicidad.egg-info/requires.txt
ginsfsm/examples/inter_event/ap4_publicidad/publicidad.egg-info/top_level.txt
